beancount_aib/__init__.py
beancount_aib/categorizer.py
beancount_aib/extractors.py
beancount_aib/importer.py
beancount_aib/importer_hook.py
beancount_aib-0.1.1.dist-info/WHEEL
beancount_aib-0.1.1.dist-info/METADATA
beancount_aib-0.1.1.dist-info/RECORD
