Metadata-Version: 2.3
Name: beancount-aib
Version: 0.1.1
Summary: Beancount importer for CSVs exported by AIB
Author: Jakub Turski
Author-email: Jakub Turski <yacoob@ftml.net>
Requires-Dist: beancount~=2.3
Requires-Dist: beancount-tx-cleanup~=0.1
Requires-Python: >=3.11
Project-URL: Repository, https://github.com/yacoob/beancount-aib
